openweatherwrap/__init__.py
openweatherwrap/_utils.py
openweatherwrap/api.py
openweatherwrap/asyncapi.py
openweatherwrap/core.py
openweatherwrap/errors.py
openweatherwrap-1.1.1.dist-info/licenses/LICENSE
openweatherwrap-1.1.1.dist-info/WHEEL
openweatherwrap-1.1.1.dist-info/METADATA
openweatherwrap-1.1.1.dist-info/RECORD
