Metadata-Version: 2.4
Name: openweatherwrap
Version: 1.1.1
Summary: A wrapper for the Openweathermap API
Author-email: lythox <lythox@lxio.dev>
Requires-Python: >=3.10
Classifier: Programming Language :: Python :: 3
License-File: LICENSE
Requires-Dist: requests>=2.32.3
Requires-Dist: geopy>=2.4.1
Requires-Dist: aiohttp>=3.12.13
Project-URL: Documentation, https://openweatherwrap.lxio.dev
Project-URL: Home, https://lxio.dev
Project-URL: Repository, https://github.com/lythoxx/openweatherwrap
